LICENSE
README.md
setup.py
gdsHelpers.egg-info/PKG-INFO
gdsHelpers.egg-info/SOURCES.txt
gdsHelpers.egg-info/dependency_links.txt
gdsHelpers.egg-info/requires.txt
gdsHelpers.egg-info/top_level.txt
gdshelpers/__init__.py
gdshelpers/_global_configuration.py
gdshelpers/export/__init__.py
gdshelpers/export/blender_export.py
gdshelpers/export/blender_import.py
gdshelpers/export/dxf_export.py
gdshelpers/export/gdsii_export.py
gdshelpers/geometry/__init__.py
gdshelpers/geometry/chip.py
gdshelpers/geometry/ebl_frame_generators.py
gdshelpers/geometry/shapely_adapter.py
gdshelpers/helpers/__init__.py
gdshelpers/helpers/alignment.py
gdshelpers/helpers/bezier.py
gdshelpers/helpers/layers.py
gdshelpers/helpers/positive_resist.py
gdshelpers/helpers/small.py
gdshelpers/helpers/under_etching.py
gdshelpers/helpers/vortex_traps.py
gdshelpers/layout/__init__.py
gdshelpers/layout/grid.py
gdshelpers/layout/write_field.py
gdshelpers/parts/__init__.py
gdshelpers/parts/_fonts.py
gdshelpers/parts/cavity.py
gdshelpers/parts/coupler.py
gdshelpers/parts/coupler_references.py
gdshelpers/parts/image.py
gdshelpers/parts/interferometer.py
gdshelpers/parts/logo.py
gdshelpers/parts/marker.py
gdshelpers/parts/mode_converter.py
gdshelpers/parts/ntron.py
gdshelpers/parts/ofwa.py
gdshelpers/parts/optical_codes.py
gdshelpers/parts/pattern_import.py
gdshelpers/parts/port.py
gdshelpers/parts/resonator.py
gdshelpers/parts/snspd.py
gdshelpers/parts/source.py
gdshelpers/parts/spiral.py
gdshelpers/parts/splitter.py
gdshelpers/parts/text.py
gdshelpers/parts/waveguide.py
gdshelpers/simulation/__init__.py
gdshelpers/simulation/simulation.py
gdshelpers/tests/__init__.py
gdshelpers/tests/test_alignment.py
gdshelpers/tests/test_chip.py
gdshelpers/tests/test_coupler.py
gdshelpers/tests/test_ebl_frame_generators.py
gdshelpers/tests/test_gdsii_export_import.py
gdshelpers/tests/test_helpers.py
gdshelpers/tests/test_port.py
gdshelpers/tests/test_positive_resist.py
gdshelpers/tests/test_resonator.py
gdshelpers/tests/test_splitter.py
gdshelpers/tests/test_waveguide.py