Metadata-Version: 2.1
Name: gdsHelpers
Version: 1.2.1
Summary: A simple Python package for creating or reading GDSII/OASIS layout files.
Home-page: UNKNOWN
Author: Helge Gehring, Matthias Blaicher, Wladick Hartmann, Wolfram Pernice
Author-email: helge.gehring@uni-muenster.de
License: LGPLv3
Project-URL: Documentation, https://gdshelpers.readthedocs.io/en/latest/
Project-URL: Bug Tracker, https://github.com/HelgeGehring/gdshelpers/issues
Project-URL: Source Code, https://github.com/HelgeGehring/gdshelpers
Platform: All
Classifier: Development Status :: 5 - Production/Stable
Classifier: Intended Audience :: Science/Research
Classifier: Topic :: Scientific/Engineering :: Electronic Design Automation (EDA)
Classifier: Topic :: Scientific/Engineering :: Physics
Classifier: Programming Language :: Python :: 3
Classifier: License :: OSI Approved :: GNU Lesser General Public License v3 (LGPLv3)
Requires-Python: >=3.5
Provides-Extra: gdspy_export
Provides-Extra: gdscad_export
Provides-Extra: oasis_export
Provides-Extra: dxf_export
Provides-Extra: image_import
Provides-Extra: image_export
Provides-Extra: mesh_export
Provides-Extra: fdtd_simulation
License-File: LICENSE
